{"name":"dll","content":{"../js/lib/jquery-2.1.1.min.js":{"id":0,"meta":{}},"../js/lib/echarts-3.8.5.min.js":{"id":1,"meta":{}},"../node_modules/webpack/buildin/global.js":{"id":2,"meta":{}},"../node_modules/webpack/buildin/module.js":{"id":3,"meta":{}},"../js/dll_less.js":{"id":4,"meta":{}},"../js/lib/geo/china.js":{"id":5,"meta":{}},"../js/lib/geo/neimenggu.js":{"id":6,"meta":{}},"../js/lib/geo/world.js":{"id":7,"meta":{}},"../js/lib/jquery.slimscroll.min.js":{"id":8,"meta":{}},"../js/lib/mdate.js":{"id":9,"meta":{}},"../js/lib/select2.min.js":{"id":10,"meta":{}},"../js/lib/velocity.min.js":{"id":11,"meta":{}},"../js/lib/vue.min.js":{"id":12,"meta":{}},"../js/lib/vuex-2.3.1.js":{"id":13,"meta":{}},"../less/vendor.less":{"id":14,"meta":{}},"../node_modules/webpack/buildin/amd-options.js":{"id":15,"meta":{}}}}